README.md
setup.py
S3N2Bin.egg-info/PKG-INFO
S3N2Bin.egg-info/SOURCES.sync-conflict-20210322-225258-YKAOKPZ.txt
S3N2Bin.egg-info/SOURCES.txt
S3N2Bin.egg-info/dependency_links.txt
S3N2Bin.egg-info/entry_points.txt
S3N2Bin.egg-info/not-zip-safe
S3N2Bin.egg-info/requires.txt
S3N2Bin.egg-info/top_level.txt
s3n2bin/cluster.py
s3n2bin/generate_coverage.py
s3n2bin/generate_kmer.py
s3n2bin/main.py
s3n2bin/main.sync-conflict-20210322-111055-TZHMZ37.py
s3n2bin/marker.hmm
s3n2bin/s3n2bin_version.py
s3n2bin/semi_supervised_model.py
s3n2bin/test_getmarker.pl
s3n2bin/utils.py
test/test_bin.py
test/test_bin.sync-conflict-20210322-111056-TZHMZ37.py
test/test_cov.py
test/test_generate_data_coassembly.py
test/test_generate_data_coassembly.sync-conflict-20210322-111056-TZHMZ37.py
test/test_generate_data_multi.py
test/test_generate_data_multi.sync-conflict-20210322-111056-TZHMZ37.py
test/test_generate_data_single.py
test/test_generate_data_single.sync-conflict-20210322-111056-TZHMZ37.py
test/test_kmer.py