Metadata-Version: 2.1
Name: S3N2Bin
Version: 0.1.1
Summary: Metagenomic binning with semi-supervised siamese neural network
Home-page: https://github.com/BigDataBiology/S3N2Bin
Author: Shaojun Pan
Author-email: shaojun1997777@gmail.com
License: MIT
Platform: UNKNOWN
Classifier: Development Status :: 3 - Alpha
Classifier: Intended Audience :: Science/Research
Classifier: Topic :: Scientific/Engineering :: Bio-Informatics
Classifier: Topic :: Scientific/Engineering :: Artificial Intelligence
Classifier: License :: OSI Approved :: MIT License
Classifier: Programming Language :: Python :: 3.6
Classifier: Programming Language :: Python :: 3.7
Classifier: Programming Language :: Python :: 3.8
